speaking_clock/__init__.py
speaking_clock/audio.py
speaking_clock/cli.py
speaking_clock/clock.py
speaking_clock/config.py
speaking_clock/const.py
speaking_clock/data/__init__.py
speaking_clock/data/clock-chime.mp3
speaking_clock/data/defaults/config.yml
speaking_clock/languages/__init__.py
speaking_clock/languages/pl.yml
speaking_clock/utils/__init__.py
speaking_clock/utils/audio_processor.py
speaking_clock/utils/number_converter.py
speaking_clock-1.0.0.dist-info/METADATA
speaking_clock-1.0.0.dist-info/WHEEL
speaking_clock-1.0.0.dist-info/entry_points.txt
speaking_clock-1.0.0.dist-info/top_level.txt
speaking_clock-1.0.0.dist-info/RECORD
