Metadata-Version: 2.4
Name: speaking-clock
Version: 1.0.0
Summary: A clock that speaks the current time using ElevenLabs API
Home-page: https://github.com/example/speaking-clock
Author: Marcin Orlowski
Author-email: Marcin Orlowski <mail@marcinorlowski.com>
License: MIT
Classifier: Programming Language :: Python :: 3
Classifier: License :: OSI Approved :: MIT License
Classifier: Operating System :: OS Independent
Requires-Python: >=3.7
Requires-Dist: elevenlabs
Requires-Dist: PyYAML
Requires-Dist: python-dateutil
Requires-Dist: num2words
Dynamic: author
Dynamic: home-page
Dynamic: requires-python
